Metadata-Version: 2.1
Name: datahand
Version: 0.0.1
Summary: DataHandler is a collection of algorithms to read and handle data for research (e.g., Web of Science, USPTO) in Python.
Home-page: https://github.com/cnavarreteliz/polapy
Author: cnavarreteliz
Author-email: cnavarreteliz@gmail.com
Classifier: Programming Language :: Python :: 3
Classifier: Programming Language :: Python :: 3.7
Classifier: Programming Language :: Python :: 3.8
Classifier: Programming Language :: Python :: 3.9
Classifier: Programming Language :: Python :: 3.10
Classifier: Programming Language :: Python :: 3.11
